LICENSE
MANIFEST.in
README.rst
setup.py
dschema/__init__.py
dschema/dschema.py
dschema.egg-info/PKG-INFO
dschema.egg-info/SOURCES.txt
dschema.egg-info/dependency_links.txt
dschema.egg-info/top_level.txt