Metadata-Version: 1.2
Name: dschema
Version: 0.3.1.3a1
Summary: Python dictionary validation by schema.
Home-page: https://github.com/Teriks/dschema
Author: Teriks
Author-email: Teriks@users.noreply.github.com
License: BSD 3-Clause
Platform: UNKNOWN
Classifier: Development Status :: 3 - Alpha
Classifier: License :: OSI Approved :: BSD License
Classifier: Intended Audience :: Developers
Classifier: Natural Language :: English
Classifier: Operating System :: OS Independent
Classifier: Topic :: Software Development :: Libraries
Requires-Python: >=3.4
